abcd_graph/__init__.py
abcd_graph/exporter.py
abcd_graph/logger.py
abcd_graph/models.py
abcd_graph/params.py
abcd_graph/utils.py
abcd_graph/version.py
abcd_graph/callbacks/__init__.py
abcd_graph/callbacks/abstract.py
abcd_graph/callbacks/property_collector.py
abcd_graph/callbacks/stats_collector.py
abcd_graph/callbacks/visualizer.py
abcd_graph/graph/__init__.py
abcd_graph/graph/community.py
abcd_graph/graph/graph.py
abcd_graph/graph/core/__init__.py
abcd_graph/graph/core/build.py
abcd_graph/graph/core/constants.py
abcd_graph/graph/core/exceptions.py
abcd_graph/graph/core/utils.py
abcd_graph/graph/core/abcd_objects/__init__.py
abcd_graph/graph/core/abcd_objects/abstract.py
abcd_graph/graph/core/abcd_objects/community.py
abcd_graph/graph/core/abcd_objects/edge.py
abcd_graph/graph/core/abcd_objects/graph_impl.py
abcd_graph/graph/core/abcd_objects/utils.py
abcd_graph-0.4.1.dist-info/METADATA
abcd_graph-0.4.1.dist-info/WHEEL
abcd_graph-0.4.1.dist-info/licenses/LICENSE
abcd_graph-0.4.1.dist-info/RECORD
