Metadata-Version: 2.4
Name: abcd-graph
Version: 0.4.1
Summary: A python library for generating ABCD graphs.
Author: Jordan Barrett
Author-email: Aleksander Wojnarowicz <alwojnarowicz@gmail.com>
License-Expression: MIT
License-File: LICENSE
Requires-Python: >=3.9
Requires-Dist: numpy>=1.26.4
Requires-Dist: typing-extensions>=4.10.0
Provides-Extra: all
Requires-Dist: igraph>=0.11.8; extra == 'all'
Requires-Dist: matplotlib>=3.9.4; extra == 'all'
Requires-Dist: networkx>=3.2.1; extra == 'all'
Requires-Dist: scipy>=1.13.1; extra == 'all'
Provides-Extra: dev
Requires-Dist: pre-commit>=4.0.1; extra == 'dev'
Requires-Dist: pytest-cov>=6.0.0; extra == 'dev'
Requires-Dist: pytest>=8.3.4; extra == 'dev'
Provides-Extra: igraph
Requires-Dist: igraph>=0.11.8; extra == 'igraph'
Provides-Extra: matplotlib
Requires-Dist: matplotlib>=3.9.4; extra == 'matplotlib'
Provides-Extra: networkx
Requires-Dist: networkx>=3.2.1; extra == 'networkx'
Provides-Extra: scipy
Requires-Dist: scipy>=1.13.1; extra == 'scipy'
